image_processing/__init__.py
image_processing/processing/__init__.py
image_processing/processing/combination.py
image_processing/processing/transformation.py
image_processing/utils/__init__.py
image_processing/utils/io.py
image_processing/utils/plot.py
package_name/__init__.py
package_name/module1_name/__init__.py
package_name/module1_name/file1_name.py
package_name/module1_name/file2_name.py
package_name/module2_name/__init__.py
package_name/module2_name/file1_name.py
package_name/module2_name/file2_name.py
DescomplicandoACriacaoDePacotes-0.0.1.dist-info/METADATA
DescomplicandoACriacaoDePacotes-0.0.1.dist-info/WHEEL
DescomplicandoACriacaoDePacotes-0.0.1.dist-info/top_level.txt
DescomplicandoACriacaoDePacotes-0.0.1.dist-info/RECORD
