Metadata-Version: 2.1
Name: DescomplicandoACriacaoDePacotes
Version: 0.0.1
Summary: DIO Project
Home-page: https://github.com/CarlVAC1980/DescomplicandoACriacaoDePacotesEmPython
Author: Carlos Valenca
Author-email: cavac10@yahoo.com.br
License: UNKNOWN
Platform: UNKNOWN
Requires-Python: >=3.8
Requires-Dist: matplotlib
Requires-Dist: numpy
Requires-Dist: scikit-image (>=0.16.1)
